{
  "totalCount": 13,
  "runningCount": 8,
  "willExpiredCount": 3,
  "expiredCount": 1,
  "changes": [
    {
      "changeId": 10000,
      "changeName": "微服务工具化",
      "endDate": "2019/10/2",
      "changeStatus": 0
    },
    {
      "changeId": 10001,
      "changeName": "新零售二期",
      "endDate": "2019/11/11",
      "changeStatus": 1
    },
    {
      "changeId": 10002,
      "changeName": "聊天接入工具",
      "endDate": "2019/12/13",
      "changeStatus": 2
    },
    {
      "changeId": 10003,
      "changeName": "顾客管理",
      "endDate": "2019/5/11",
      "changeStatus": 3
    }
  ]

}